ensae_teaching_dl/__init__.py
ensae_teaching_dl/examples/__init__.py
ensae_teaching_dl/examples/keras_mnist.py
ensae_teaching_dl/faq/__init__.py
ensae_teaching_dl/faq/faq_gpu.py
ensae_teaching_dl-0.2.162.dist-info/LICENSE.txt
ensae_teaching_dl-0.2.162.dist-info/METADATA
ensae_teaching_dl-0.2.162.dist-info/WHEEL
ensae_teaching_dl-0.2.162.dist-info/top_level.txt
ensae_teaching_dl-0.2.162.dist-info/RECORD
