Metadata-Version: 2.1
Name: ensae-teaching-dl
Version: 0.2.162
Summary: Materials for teachings about deep learning, mostly in French.
Home-page: http://www.xavierdupre.fr/app/ensae_teaching_dl/helpsphinx/index.html
Author: Xavier Dupré
Author-email: xavier.dupre@gmail.com
License: MIT
Download-URL: https://github.com/sdpython/ensae_teaching_dl/
Keywords: ensae_teaching_dl,Xavier Dupré
Platform: UNKNOWN
Classifier: Programming Language :: Python :: 3
Classifier: Intended Audience :: Developers
Classifier: Topic :: Scientific/Engineering
Classifier: Topic :: Education
Classifier: License :: OSI Approved :: MIT License
Classifier: Development Status :: 5 - Production/Stable
Requires-Dist: keras
Requires-Dist: torch
